ConfToolAPI/APIHandler.py
ConfToolAPI/__init__.py
ConfToolAPI-1.0.0.dist-info/METADATA
ConfToolAPI-1.0.0.dist-info/WHEEL
ConfToolAPI-1.0.0.dist-info/top_level.txt
ConfToolAPI-1.0.0.dist-info/RECORD
