Metadata-Version: 2.1
Name: ConfToolAPI
Version: 1.0.0
Summary: Methods to query the ConfTool API
Home-page: https://github.com/llamm-de/conftool-python
Author: Lukas Lamm
Author-email: lukas.lamm@mailbox.org
License: MIT License
Keywords: conftool,api
Classifier: Programming Language :: Python :: 3
Classifier: License :: OSI Approved :: MIT License
Classifier: Operating System :: OS Independent
Requires-Dist: requests
Requires-Dist: xmltodict
